stealth/__init__.py
stealth/main.py
driver_stealth-0.0.1.dist-info/LICENSE
driver_stealth-0.0.1.dist-info/METADATA
driver_stealth-0.0.1.dist-info/WHEEL
driver_stealth-0.0.1.dist-info/top_level.txt
driver_stealth-0.0.1.dist-info/RECORD
